json_repr/__init__.py
json_repr/dumps.py
json_repr/mongo_db.py
json_repr-1.1.12.dist-info/METADATA
json_repr-1.1.12.dist-info/WHEEL
json_repr-1.1.12.dist-info/licenses/LICENSE
json_repr-1.1.12.dist-info/RECORD
