Metadata-Version: 2.1
Name: json_repr
Version: 1.1.12
Summary: Handle JSON like data structures with a "repr(...)" fallback, e.g. for MongoDB types
Project-URL: Homepage, https://github.com/clxx/json-repr
Project-URL: Bug Tracker, https://github.com/clxx/json-repr/issues
Author-email: Carsten Lindner <Carsten.Lindner@gmx.net>
License-File: LICENSE
Keywords: JSON,MongoDB,dumps,eval,repr
Classifier: License :: OSI Approved :: MIT License
Classifier: Operating System :: OS Independent
Classifier: Programming Language :: Python :: 3
Requires-Python: >=3.6
